setup.py
vanilla_dsnd_probability/Binomialdistribution.py
vanilla_dsnd_probability/Gaussiandistribution.py
vanilla_dsnd_probability/Generaldistribution.py
vanilla_dsnd_probability/__init__.py
vanilla_dsnd_probability.egg-info/PKG-INFO
vanilla_dsnd_probability.egg-info/SOURCES.txt
vanilla_dsnd_probability.egg-info/dependency_links.txt
vanilla_dsnd_probability.egg-info/not-zip-safe
vanilla_dsnd_probability.egg-info/top_level.txt