Metadata-Version: 1.0
Name: vanilla-dsnd-probability
Version: 0.1
Summary: Gaussian distributions
Home-page: UNKNOWN
Author: Shakthivanilla
Author-email: shakthivanilla@gmail.com
License: UNKNOWN
Platform: UNKNOWN
